drb_impl_file/__init__.py
drb_impl_file/_version.py
drb_impl_file/cortex.yml
drb_impl_file/drb_impl_file.py
drb_impl_file/execptions.py
drb_impl_file-1.0.1.data/data/requirements.txt
drb_impl_file-1.0.1.dist-info/METADATA
drb_impl_file-1.0.1.dist-info/WHEEL
drb_impl_file-1.0.1.dist-info/entry_points.txt
drb_impl_file-1.0.1.dist-info/top_level.txt
drb_impl_file-1.0.1.dist-info/RECORD
